rooibos/__init__.py
rooibos/exceptions.py
rooibos/version.py
rooibos-0.4.1.dist-info/METADATA
rooibos-0.4.1.dist-info/WHEEL
rooibos-0.4.1.dist-info/top_level.txt
rooibos-0.4.1.dist-info/RECORD
