Metadata-Version: 2.1
Name: rooibos
Version: 0.4.1
Summary: Lightweight language-independent syntax rewriting.
Home-page: https://github.com/squaresLab/rooibos.py
Author: Chris Timperley, Rijnard van Tonder
Author-email: christimperley@googlemail.com
License: mit
Platform: UNKNOWN
Classifier: Natural Language :: English
Classifier: Programming Language :: Python
Classifier: Programming Language :: Python :: 2
Classifier: Programming Language :: Python :: 2.7
Classifier: Programming Language :: Python :: 3
Classifier: Programming Language :: Python :: 3.5
Classifier: Programming Language :: Python :: 3.6
Requires-Python: >=2.7
Requires-Dist: requests (>=2.0.0)
Requires-Dist: typing (>=0.4.1)
